dbrequests/__init__.py
dbrequests/connection.py
dbrequests/database.py
dbrequests/query.py
dbrequests/temp_file.py
dbrequests/mysql/__init__.py
dbrequests/mysql/connection.py
dbrequests/mysql/database.py
dbrequests/mysql/tests/__init__.py
dbrequests/mysql/tests/conftest.py
dbrequests/mysql/tests/test_connection.py
dbrequests/mysql/tests/test_send_data.py
dbrequests/mysql/tests/test_send_delete.py
dbrequests/mysql/tests/test_send_query.py
dbrequests/tests/__init__.py
dbrequests/tests/conftest.py
dbrequests/tests/test_connection.py
dbrequests/tests/test_database.py
dbrequests/tests/test_query.py
dbrequests-1.4.8.dist-info/LICENSE
dbrequests-1.4.8.dist-info/METADATA
dbrequests-1.4.8.dist-info/WHEEL
dbrequests-1.4.8.dist-info/top_level.txt
dbrequests-1.4.8.dist-info/RECORD
