Metadata-Version: 2.1
Name: dbrequests
Version: 1.4.8
Summary: Python package for querying and connecting to databases.
Home-page: https://github.com/INWTlab/dbrequests
Author: Matthaeus Deutsch
Author-email: mdeutsch@outlook.com
License: MIT
Platform: UNKNOWN
Classifier: Development Status :: 4 - Beta
Classifier: Intended Audience :: Developers
Classifier: Natural Language :: English
Classifier: License :: OSI Approved :: MIT License
Classifier: Programming Language :: Python
Classifier: Programming Language :: Python :: 3
Classifier: Programming Language :: Python :: 3.4
Classifier: Programming Language :: Python :: 3.5
Classifier: Programming Language :: Python :: 3.6
Classifier: Programming Language :: Python :: 3.7
Classifier: Programming Language :: Python :: 3.8
Requires-Dist: pandas
Requires-Dist: SQLAlchemy ; python_version >= "3.0"
Provides-Extra: mysql
Requires-Dist: datatable ; extra == 'mysql'
Provides-Extra: pg
Requires-Dist: psycopg2 ; extra == 'pg'
Provides-Extra: redshift
Requires-Dist: sqlalchemy-redshift ; extra == 'redshift'
Requires-Dist: psycopg2 ; extra == 'redshift'
